tier_techdocs_core/__init__.py
tier_techdocs_core/core.py
tier_techdocs_core/test_core.py
tier_mkdocs_techdocs_core-0.0.10.dist-info/LICENSE
tier_mkdocs_techdocs_core-0.0.10.dist-info/METADATA
tier_mkdocs_techdocs_core-0.0.10.dist-info/WHEEL
tier_mkdocs_techdocs_core-0.0.10.dist-info/entry_points.txt
tier_mkdocs_techdocs_core-0.0.10.dist-info/top_level.txt
tier_mkdocs_techdocs_core-0.0.10.dist-info/RECORD
