Metadata-Version: 2.1
Name: tier-mkdocs-techdocs-core
Version: 0.0.10
Summary: The core MkDocs plugin used by Backstage's TechDocs as a wrapper around multiple MkDocs plugins and Python Markdown extensions - Customized by TIER Mobility SE.
Home-page: https://github.com/TierMobility/tier-mkdocs-techdocs-core
Author: TIER Mobility DX Team
Author-email: dx@tier.app
License: Apache-2.0
Keywords: mkdocs
Platform: UNKNOWN
Classifier: Development Status :: 3 - Alpha
Classifier: Intended Audience :: Developers
Classifier: Intended Audience :: Information Technology
Classifier: License :: OSI Approved :: Apache Software License
Classifier: Programming Language :: Python
Classifier: Programming Language :: Python :: 3 :: Only
Classifier: Programming Language :: Python :: 3.7
Requires-Python: >=3.7
Requires-Dist: mkdocs (>=1.2.2)
Requires-Dist: mkdocs-material (==8.1.11)
Requires-Dist: mkdocs-monorepo-plugin (~=1.0.1)
Requires-Dist: mkdocs-kroki-plugin (>=0.3.0)
Requires-Dist: plantuml-markdown (==3.5.0)
Requires-Dist: pyparsing (==2.4.7)
Requires-Dist: markdown-inline-graphviz-extension (==1.1)
Requires-Dist: mdx-truly-sane-lists (==1.2)
Requires-Dist: pygments (==2.10)
Requires-Dist: pymdown-extensions (==9.3)
Requires-Dist: Markdown (==3.2.2)
Requires-Dist: Jinja2 (==3.0.3)
